{
  "lastUpdated": "05:23 PM, 27 April 2026",
  "Ek Din [2D | Hindi]": {
    "2026-05-01": {
      "CINEPOLIS": [
        12,
        113,
        12,
        34174.34,
        6.17
      ],
      "PVR": [
        78,
        792,
        42,
        287853.83,
        5.73
      ],
      "INOX": [
        77,
        505,
        31,
        185820,
        3.75
      ]
    },
    "2026-05-02": {
      "CINEPOLIS": [
        8,
        9,
        4,
        2841.43,
        0.74
      ],
      "PVR": [
        68,
        0,
        17,
        0,
        0.0
      ],
      "INOX": [
        77,
        149,
        19,
        49830,
        1.23
      ]
    }
  },
  "The Devil Wears Prada 2 [2D | English]": {
    "2026-05-01": {
      "CINEPOLIS": [
        169,
        1806,
        67,
        591301.01,
        5.94
      ],
      "PVR": [
        90,
        2326,
        20,
        1742599.81,
        13.94
      ],
      "INOX": [
        43,
        307,
        13,
        231350,
        4.34
      ]
    },
    "2026-05-02": {
      "CINEPOLIS": [
        143,
        825,
        63,
        272843.83,
        3.2
      ],
      "PVR": [
        93,
        1665,
        20,
        1305483.33,
        9.25
      ],
      "INOX": [
        39,
        275,
        11,
        195520,
        4.29
      ]
    }
  },
  "The Devil Wears Prada 2 [SCREEN X | English]": {
    "2026-05-01": {
      "INOX": [
        6,
        6,
        1,
        4240,
        0.65
      ]
    },
    "2026-05-02": {
      "INOX": [
        6,
        0,
        1,
        0,
        0.0
      ]
    }
  },
  "Raja Shivaji [2D | Marathi]": {
    "2026-05-01": {
      "CINEPOLIS": [
        36,
        933,
        9,
        311944.35,
        15.96
      ],
      "PVR": [
        47,
        1210,
        11,
        354737.51,
        9.04
      ],
      "INOX": [
        47,
        1384,
        10,
        398120,
        10.93
      ]
    },
    "2026-05-02": {
      "CINEPOLIS": [
        32,
        141,
        9,
        44685.1,
        2.74
      ],
      "PVR": [
        48,
        207,
        11,
        65816.93,
        1.54
      ],
      "INOX": [
        43,
        295,
        10,
        89380,
        2.54
      ]
    }
  },
  "Raja Shivaji [2D | Hindi]": {
    "2026-05-01": {
      "CINEPOLIS": [
        5,
        11,
        1,
        3661.43,
        1.48
      ]
    },
    "2026-05-02": {
      "CINEPOLIS": [
        5,
        6,
        1,
        1776.0,
        0.81
      ]
    }
  }
}